{"assets":{"C7B33B853BB312F0A0A6A5ED301CBF30":{"type":"texture","index":1,"assetRequest":{"type":"slide","state":"contents","slide":"none"},"url":{"native":"assets\/932BE601-1F31-4DAD-8FCA-9ABCE2CAE225.pdf"},"width":1920,"height":1080},"C37D66AFF6DC9EB30F67D365B5E53359":{"type":"texture","index":0,"assetRequest":{"type":"slide","state":"contents","slide":"none"},"url":{"native":"assets\/932BE601-1F31-4DAD-8FCA-9ABCE2CAE225.pdf"},"width":1920,"height":1080}},"events":[{"effects":[{"beginTime":0,"baseLayer":{"animations":[],"initialState":{"affineTransform":[1,0,0,1,0,0],"masksToBounds":false,"rotation":0,"scale":1,"position":{"pointX":960,"pointY":540},"width":1920,"sublayerTransform":[1,0,0,0,0,1,0,0,0,0,1,0,0,0,0,1],"contentsRect":{"y":0,"x":0,"width":1,"height":1},"opacity":1,"edgeAntialiasingMask":251658240,"height":1080,"hidden":false,"anchorPoint":{"pointX":0.5,"pointY":0.5}},"objectID":"0","layers":[{"animations":[],"initialState":{"affineTransform":[1,0,0,1,0,0],"masksToBounds":false,"rotation":0,"scale":1,"position":{"pointX":960,"pointY":540},"width":1920,"sublayerTransform":[1,0,0,0,0,1,0,0,0,0,1,-0.00035007912466775983,0,0,0,1],"contentsRect":{"y":0,"x":0,"width":1,"height":1},"opacity":1,"edgeAntialiasingMask":251658240,"height":1080,"hidden":false,"anchorPoint":{"pointX":0.5,"pointY":0.5}},"layers":[{"animations":[],"layers":[],"texturedRectangle":{"isBackgroundTexture":false,"singleTextureOpacity":1,"textureType":0,"textBaseline":0,"textXHeight":0,"isVerticalText":false},"initialState":{"affineTransform":[1,0,0,1,0,0],"masksToBounds":false,"rotation":0,"scale":1,"position":{"pointX":960,"pointY":540},"width":1920,"sublayerTransform":[1,0,0,0,0,1,0,0,0,0,1,0,0,0,0,1],"contentsRect":{"y":0,"x":0,"width":1,"height":1},"opacity":1,"edgeAntialiasingMask":0,"height":1080,"hidden":false,"anchorPoint":{"pointX":0.5,"pointY":0.5}},"texture":"C7B33B853BB312F0A0A6A5ED301CBF30"},{"animations":[{"timeOffset":0,"from":{"scalar":false},"beginTime":0,"repeatCount":0,"fillMode":"both","property":"hidden","autoreverses":false,"duration":0.01,"to":{"scalar":true}}],"layers":[],"texturedRectangle":{"isBackgroundTexture":false,"singleTextureOpacity":1,"textureType":0,"textBaseline":0,"textXHeight":0,"isVerticalText":false},"initialState":{"affineTransform":[1,0,0,1,0,0],"masksToBounds":false,"rotation":0,"scale":1,"position":{"pointX":960,"pointY":540},"width":1920,"sublayerTransform":[1,0,0,0,0,1,0,0,0,0,1,0,0,0,0,1],"contentsRect":{"y":0,"x":0,"width":1,"height":1},"opacity":1,"edgeAntialiasingMask":0,"height":1080,"hidden":false,"anchorPoint":{"pointX":0.5,"pointY":0.5}},"texture":"C37D66AFF6DC9EB30F67D365B5E53359"}]}]},"effects":[],"duration":0.01,"type":"transition","name":"none","objectID":"0"}],"automaticPlay":false,"hyperlinks":[],"accessibility":[{"text":"> predict(reg1, africa)","targetRectangle":{"y":252.25341796875,"x":95.922149658203125,"width":772.92578125,"height":67}},{"text":"        1         2         3         4         5         6         7         8 ","targetRectangle":{"y":362.25341796875,"x":95.922149658203125,"width":1728.28125,"height":43}},{"text":"126764.61  54518.55  23402.63  27248.31  28044.37  20060.58  40531.52  16458.32 ","targetRectangle":{"y":405.25341796875,"x":95.922149658203125,"width":1728.28125,"height":43}},{"text":"        9        10        11        12        13        14        15        16 ","targetRectangle":{"y":448.25341796875,"x":95.922149658203125,"width":1728.28125,"height":43}},{"text":" 17613.22  23907.08  15720.62  51229.25  22388.39  40768.04  16639.83 237823.61 ","targetRectangle":{"y":491.25341796875,"x":95.922149658203125,"width":1728.28125,"height":43}},{"text":"       17        18        19        20        21        22        23        24 ","targetRectangle":{"y":534.25341796875,"x":95.922149658203125,"width":1728.28125,"height":43}},{"text":" 19968.69  17947.20  80898.27  24049.88  16545.73  43550.15  24717.92  16131.68 ","targetRectangle":{"y":577.25341796875,"x":95.922149658203125,"width":1728.28125,"height":43}},{"text":"       25        26        27        28        29        30        31        32 ","targetRectangle":{"y":620.25341796875,"x":95.922149658203125,"width":1728.28125,"height":43}},{"text":" 58146.41  17343.62  17676.58  34169.52  29237.12  24442.74  26954.44  18527.76 ","targetRectangle":{"y":663.25341796875,"x":95.922149658203125,"width":1728.28125,"height":43}},{"text":"       33        34        35        36        37        38        39        40 ","targetRectangle":{"y":706.25341796875,"x":95.922149658203125,"width":1728.28125,"height":43}},{"text":" 24027.01 102598.67  37998.99  23993.94  25920.52 213084.67  24901.98  15403.75 ","targetRectangle":{"y":749.25341796875,"x":95.922149658203125,"width":1728.28125,"height":43}},{"text":"       41        42        43        44        45        46        47        48 ","targetRectangle":{"y":792.25341796875,"x":95.922149658203125,"width":1728.28125,"height":43}},{"text":" 29774.56  16455.21  19351.85  18804.40 240968.75  55287.57  17776.99  63557.34 ","targetRectangle":{"y":835.25341796875,"x":95.922149658203125,"width":1728.28125,"height":43}},{"text":"       49        50        51        52        53 ","targetRectangle":{"y":878.25341796875,"x":95.922149658203125,"width":1080.17578125,"height":43}},{"text":" 19758.43  51857.54  45500.02  29023.89  26232.97 ","targetRectangle":{"y":921.25341796875,"x":95.922149658203125,"width":1080.17578125,"height":43}},{"text":"Prediction","targetRectangle":{"y":34,"x":646.18999999999994,"width":627.62,"height":168}}],"baseLayer":{"animations":[],"initialState":{"affineTransform":[1,0,0,1,0,0],"masksToBounds":false,"rotation":0,"scale":1,"position":{"pointX":960,"pointY":540},"width":1920,"sublayerTransform":[1,0,0,0,0,1,0,0,0,0,1,0,0,0,0,1],"contentsRect":{"y":0,"x":0,"width":1,"height":1},"opacity":1,"edgeAntialiasingMask":251658240,"height":1080,"hidden":false,"anchorPoint":{"pointX":0.5,"pointY":0.5}},"objectID":"0","layers":[{"animations":[],"initialState":{"affineTransform":[1,0,0,1,0,0],"masksToBounds":false,"rotation":0,"scale":1,"position":{"pointX":960,"pointY":540},"width":1920,"sublayerTransform":[1,0,0,0,0,1,0,0,0,0,1,-0.00035007912466775983,0,0,0,1],"contentsRect":{"y":0,"x":0,"width":1,"height":1},"opacity":1,"edgeAntialiasingMask":251658240,"height":1080,"hidden":false,"anchorPoint":{"pointX":0.5,"pointY":0.5}},"layers":[{"animations":[],"layers":[],"texturedRectangle":{"isBackgroundTexture":false,"singleTextureOpacity":1,"textureType":0,"textBaseline":0,"textXHeight":0,"isVerticalText":false},"initialState":{"affineTransform":[1,0,0,1,0,0],"masksToBounds":false,"rotation":0,"scale":1,"position":{"pointX":960,"pointY":540},"width":1920,"sublayerTransform":[1,0,0,0,0,1,0,0,0,0,1,0,0,0,0,1],"contentsRect":{"y":0,"x":0,"width":1,"height":1},"opacity":1,"edgeAntialiasingMask":0,"height":1080,"hidden":false,"anchorPoint":{"pointX":0.5,"pointY":0.5}},"texture":"C37D66AFF6DC9EB30F67D365B5E53359"}]}]}}]}